MANIFEST.in
README.rst
setup.py
IOSSHy.egg-info/PKG-INFO
IOSSHy.egg-info/SOURCES.txt
IOSSHy.egg-info/dependency_links.txt
IOSSHy.egg-info/top_level.txt
bin/iosshy
iosshy/Ui_tunneldialog.py
iosshy/__init__.py
iosshy/application.py
iosshy/icons_rc.py
iosshy/tray.py
iosshy/tunnel.py
iosshy/tunneldialog.py
iosshy/tunneldialog.ui