Metadata-Version: 1.1
Name: IOSSHy
Version: 1.5
Summary: Desktop tool to quickly setup SSH tunnels and automatically execute commands that make use of them
Home-page: http://github.com/mtorromeo/iosshy
Author: Massimiliano Torromeo
Author-email: massimiliano.torromeo@gmail.com
License: BSD License
Download-URL: http://github.com/mtorromeo/iosshy/tarball/v1.5
Keywords: qt,pyqt,desktop,ssh
Platform: UNKNOWN
Classifier: Programming Language :: Python
Classifier: Programming Language :: Python :: 2.6
Classifier: Programming Language :: Python :: 2.7
Classifier: Development Status :: 5 - Production/Stable
Classifier: License :: OSI Approved :: BSD License
Classifier: Environment :: X11 Applications :: Qt
Classifier: Intended Audience :: System Administrators
Classifier: Operating System :: MacOS :: MacOS X
Classifier: Operating System :: Microsoft :: Windows
Classifier: Operating System :: POSIX :: Linux
Classifier: Operating System :: POSIX :: BSD
Classifier: Natural Language :: English
Classifier: Topic :: System :: Monitoring
Classifier: Topic :: Utilities
Requires: paramiko
Requires: keyring
Requires: setproctitle
